paho_mqtt_helper/__init__.py
paho_mqtt_helper/mqtt_helper.py
paho_mqtt_helper-0.0.1.dist-info/LICENSE
paho_mqtt_helper-0.0.1.dist-info/METADATA
paho_mqtt_helper-0.0.1.dist-info/WHEEL
paho_mqtt_helper-0.0.1.dist-info/top_level.txt
paho_mqtt_helper-0.0.1.dist-info/RECORD
